{
  "dynamic-yield": {
    "Alpha": {
      "events": [
        {
          "id": "9864d6a6-5e0f-4200-b119-3358fe9e4d58",
          "start": "2019-11-25T20:30:00.000Z",
          "end": "2019-11-25T21:00:00.000Z",
          "title": "sada"
        }
      ]
    },
    "Bravo": {
      "events": [
        {
          "id": "bb8e4e6d-f4ab-4f5a-8efa-c91a376f4ddb",
          "start": "2019-11-25T20:00:00.000Z",
          "end": "2019-11-25T21:00:00.000Z",
          "title": "event1"
        },
        {
          "id": "ca3a0851-f1c5-455a-b66e-2716ce0ebd90",
          "start": "2019-11-25T18:30:00.000Z",
          "end": "2019-11-25T20:00:00.000Z",
          "title": "event2"
        },
        {
          "id": "66e85bd2-6899-42c2-a482-c1c76532fbfc",
          "start": "2019-11-24T23:30:00.000Z",
          "end": "2019-11-25T02:00:00.000Z",
          "title": "ssad"
        },
        {
          "id": "3e672085-e808-4637-bdc1-d35986750736",
          "start": "2019-11-25T21:00:00.000Z",
          "end": "2019-11-25T21:59:59.999Z",
          "title": "ssdfsd"
        }
      ]
    },
    "Charlie": {
      "events": [
        {
          "id": "dfaa8281-8bb7-4511-ba8a-b047d74516c7",
          "start": "2019-11-25T18:30:00.000Z",
          "end": "2019-11-25T20:00:00.000Z",
          "title": "asdasdas"
        }
      ]
    }
  }
}